cloudflare_fuzzy_finder/__init__.py
cloudflare_fuzzy_finder/cf_utils.py
cloudflare_fuzzy_finder/main.py
cloudflare_fuzzy_finder/settings.py
cloudflare_fuzzy_finder/libs/fzf-0.17.0-darwin_386
cloudflare_fuzzy_finder/libs/fzf-0.17.0-darwin_amd64
cloudflare_fuzzy_finder/libs/fzf-0.17.0-linux_386
cloudflare_fuzzy_finder/libs/fzf-0.17.0-linux_amd64
cloudflare_fuzzy_finder-0.1.4.dist-info/METADATA
cloudflare_fuzzy_finder-0.1.4.dist-info/RECORD
cloudflare_fuzzy_finder-0.1.4.dist-info/WHEEL
cloudflare_fuzzy_finder-0.1.4.dist-info/entry_points.txt
cloudflare_fuzzy_finder-0.1.4.dist-info/top_level.txt
