Metadata-Version: 2.1
Name: cloudflare-fuzzy-finder
Version: 0.1.4
Summary: Find cloudflare DNS records using fuzzy search.
Home-page: https://github.com/dhoeric/cloudflare-fuzzy-finder
Author: Eric Ho
Author-email: dho.eric@gmail.com
License: MIT
Download-URL: https://github.com/dhoeric/cloudflare-fuzzy-finder/tarball/master
Keywords: cloudflare,fuzzy,dns
Platform: UNKNOWN
Classifier: Development Status :: 5 - Production/Stable
Classifier: Intended Audience :: Developers
Classifier: Intended Audience :: System Administrators
Classifier: License :: OSI Approved :: MIT License
Classifier: Programming Language :: Python
Classifier: Programming Language :: Python :: 2.7
Classifier: Programming Language :: Python :: 3
Classifier: Programming Language :: Python :: 3.4
Classifier: Programming Language :: Python :: 3.5
Classifier: Programming Language :: Python :: 3.6
Requires-Dist: click (==6.6)
Requires-Dist: cloudflare (==2.1.0)
